alegra/__init__.py
alegra/api_requestor.py
alegra/resources/__init__.py
alegra/resources/contact.py
alegra/resources/invoice.py
alegra/resources/item.py
alegra/resources/retention.py
alegra/resources/tax.py
alegra/resources/abstract/__init__.py
alegra/resources/abstract/api_resource.py
alegra/resources/abstract/createable_api_resource.py
alegra/resources/abstract/deletable_api_resource.py
alegra/resources/abstract/emailable_api_resource.py
alegra/resources/abstract/listable_api_resource.py
alegra/resources/abstract/updateable_api_resource.py
alegra/resources/abstract/voidable_api_resource.py
alegra-0.1.1.dist-info/LICENSE
alegra-0.1.1.dist-info/METADATA
alegra-0.1.1.dist-info/WHEEL
alegra-0.1.1.dist-info/top_level.txt
alegra-0.1.1.dist-info/RECORD
